aio_microservice-0.15.0.dist-info/METADATA
aio_microservice-0.15.0.dist-info/WHEEL
aio_microservice-0.15.0.dist-info/licenses/LICENSE
aio_microservice/__init__.py
aio_microservice/__version__.py
aio_microservice/amqp/__init__.py
aio_microservice/amqp/asyncapi.py
aio_microservice/amqp/extension.py
aio_microservice/amqp/testing.py
aio_microservice/core/__init__.py
aio_microservice/core/abc.py
aio_microservice/core/logging.py
aio_microservice/core/openapi.py
aio_microservice/core/service.py
aio_microservice/core/testing.py
aio_microservice/graphql/__init__.py
aio_microservice/graphql/extension.py
aio_microservice/http.py
aio_microservice/http_cors/__init__.py
aio_microservice/http_cors/extension.py
aio_microservice/prometheus/__init__.py
aio_microservice/prometheus/extension.py
aio_microservice/py.typed
aio_microservice/s3/__init__.py
aio_microservice/s3/extension.py
aio_microservice/scheduler/__init__.py
aio_microservice/scheduler/extension.py
aio_microservice/types.py
aio_microservice-0.15.0.dist-info/RECORD
