Metadata-Version: 2.1
Name: aio-microservice
Version: 0.15.0
Summary: A library to create microservices.
Author-Email: betaboon <betaboon@0x80.ninja>
Maintainer-Email: betaboon <betaboon@0x80.ninja>
License: MIT
Classifier: Development Status :: 2 - Pre-Alpha
Classifier: Intended Audience :: Developers
Classifier: License :: OSI Approved :: MIT License
Classifier: Natural Language :: English
Classifier: Operating System :: OS Independent
Classifier: Programming Language :: Python
Classifier: Programming Language :: Python :: 3
Classifier: Programming Language :: Python :: 3 :: Only
Classifier: Programming Language :: Python :: 3.9
Classifier: Programming Language :: Python :: 3.10
Classifier: Programming Language :: Python :: 3.11
Classifier: Programming Language :: Python :: 3.12
Classifier: Typing :: Typed
Project-URL: Homepage, https://github.com/betaboon/aio-microservice
Project-URL: Documentation, https://betaboon.github.io/aio-microservice
Project-URL: Changelog, https://github.com/betaboon/aio-microservice/releases
Project-URL: Repository, https://github.com/betaboon/aio-microservice
Project-URL: Issue tracker, https://github.com/betaboon/aio-microservice/issues
Requires-Python: <3.13,>=3.9
Requires-Dist: annotated-types>=0.7.0
Requires-Dist: click>=8.1.3
Requires-Dist: eval-type-backport>=0.2.0; python_version < "3.10"
Requires-Dist: litestar>=2.9.1
Requires-Dist: loguru>=0.7.2
Requires-Dist: pydantic>=2.7.4
Requires-Dist: pyhumps>=3.8.0
Requires-Dist: rich-click>=1.8.3
Requires-Dist: rich>=13.7.1
Requires-Dist: typed-settings>=24.3.0
Requires-Dist: typing-extensions>=4.12.2
Requires-Dist: uvicorn>=0.30.1
Requires-Dist: faststream[rabbit]>=0.5.13; extra == "amqp"
Requires-Dist: pyyaml>=6.0.1; extra == "amqp"
Requires-Dist: aio-microservice[amqp]; extra == "all"
Requires-Dist: aio-microservice[graphql]; extra == "all"
Requires-Dist: aio-microservice[prometheus]; extra == "all"
Requires-Dist: aio-microservice[s3]; extra == "all"
Requires-Dist: aio-microservice[scheduler]; extra == "all"
Requires-Dist: boto3>=1.34.132; extra == "s3"
Requires-Dist: apscheduler>=3.10.4; extra == "scheduler"
Requires-Dist: strawberry-graphql>=0.235.0; extra == "graphql"
Requires-Dist: websockets>=12.0; extra == "graphql"
Requires-Dist: litestar[prometheus]>=2.9.1; extra == "prometheus"
Requires-Dist: prometheus-client>=0.20.0; extra == "prometheus"
Provides-Extra: amqp
Provides-Extra: all
Provides-Extra: s3
Provides-Extra: scheduler
Provides-Extra: graphql
Provides-Extra: prometheus
